fast_proxy_list/__init__.py
fast_proxy_list/proxies.py
fast_proxy_list/test.py
fast_proxy_list-0.0.2.dist-info/LICENCE
fast_proxy_list-0.0.2.dist-info/METADATA
fast_proxy_list-0.0.2.dist-info/WHEEL
fast_proxy_list-0.0.2.dist-info/top_level.txt
fast_proxy_list-0.0.2.dist-info/RECORD
